simple_sonarqube_api/__init__.py
simple_sonarqube_api/_http.py
simple_sonarqube_api/client.py
simple_sonarqube_api/exceptions.py
simple_sonarqube_api/models.py
simple_sonarqube_api-0.1.6.dist-info/licenses/LICENSE
simple_sonarqube_api-0.1.6.dist-info/METADATA
simple_sonarqube_api-0.1.6.dist-info/WHEEL
simple_sonarqube_api-0.1.6.dist-info/top_level.txt
simple_sonarqube_api-0.1.6.dist-info/RECORD
