Metadata-Version: 2.4
Name: simple-sonarqube-api
Version: 0.1.6
Summary: Simple Python client for SonarQube Web API
Author: M.E. (Mikehenrytech)
License-Expression: GPL-3.0-only
Requires-Python: >=3.10
License-File: LICENSE
Requires-Dist: requests>=2.32
Provides-Extra: dev
Requires-Dist: pytest>=8; extra == "dev"
Requires-Dist: responses>=0.25; extra == "dev"
Requires-Dist: ruff>=0.6; extra == "dev"
Requires-Dist: mypy>=1.11; extra == "dev"
Requires-Dist: python-dotenv>=1.2.1; extra == "dev"
Dynamic: license-file
